shipyard_magnite/__init__.py
shipyard_magnite/cli/authtest.py
shipyard_magnite/cli/update.py
shipyard_magnite/errs.py
shipyard_magnite/magnite.py
shipyard_magnite-0.1.0.dist-info/METADATA
shipyard_magnite-0.1.0.dist-info/WHEEL
shipyard_magnite-0.1.0.dist-info/RECORD
