Metadata-Version: 2.1
Name: shipyard-magnite
Version: 0.1.0
Summary: 
Author: wrp801
Author-email: wespoulsen@gmail.com
Requires-Python: >=3.9,<4.0
Classifier: Programming Language :: Python :: 3
Classifier: Programming Language :: Python :: 3.9
Classifier: Programming Language :: Python :: 3.10
Classifier: Programming Language :: Python :: 3.11
Classifier: Programming Language :: Python :: 3.12
Requires-Dist: pandas (>=2.0,<3.0)
Requires-Dist: requests (>=2.32.3,<3.0.0)
Requires-Dist: shipyard-templates (==0.10.0a0)
